ovf2io/__init__.py
ovf2io/_rect_utils.py
ovf2io/_templates.py
ovf2io/_utils.py
ovf2io-0.10.1.dist-info/LICENSE
ovf2io-0.10.1.dist-info/METADATA
ovf2io-0.10.1.dist-info/WHEEL
ovf2io-0.10.1.dist-info/top_level.txt
ovf2io-0.10.1.dist-info/RECORD
