Metadata-Version: 2.1
Name: ovf2io
Version: 0.10.1
Summary: Utility for reading and writing OOMMF Vector Field (.ovf) format. 
Home-page: https://github.com/McMorranLab/ovf2io
Author: William S. Parker
Author-email: "William S. Parker" <will.parker0@gmail.com>
License: GNU GENERAL PUBLIC LICENSE
Project-URL: Homepage, https://github.com/McMorranLab/ovf2io
Project-URL: Bug Tracker, https://github.com/McMorranLab/ovf2io/issues
Project-URL: Documentation, https://mcmorranlab.github.io/ovf2io/
Classifier: Programming Language :: Python :: 3
Classifier: License :: OSI Approved :: GNU General Public License v3 (GPLv3)
Classifier: Operating System :: OS Independent
Requires-Python: >=3.6
License-File: LICENSE
Requires-Dist: numpy
